{
  "round": 470,
  "date": "2011-12-03",
  "nums": [
    10,
    16,
    20,
    39,
    41,
    42
  ],
  "bonus": 27,
  "firstWinAmount": 4333330625,
  "firstWinners": 3,
  "totalSales": 53912965000,
  "prizes": {
    "first": {
      "amount": 4333330625,
      "winners": 3
    },
    "second": {
      "amount": 80246864,
      "winners": 27
    },
    "third": {
      "amount": 1558753,
      "winners": 1390
    },
    "fourth": {
      "amount": 50000,
      "winners": 71706
    },
    "fifth": {
      "amount": 5000,
      "winners": 1207572
    }
  },
  "methodCounts": {
    "auto": 3,
    "manual": 0,
    "mixed": 0
  },
  "topStores": [
    {
      "rank": 1,
      "name": "천하제일복권명당",
      "address": "대전 중구 태평동  377-4번지",
      "method": "auto",
      "lat": 36.326427,
      "lng": 127.394844
    },
    {
      "rank": 1,
      "name": "가자복권천국",
      "address": "전남 목포시 신흥로45번길 2",
      "method": "auto",
      "lat": 34.803482,
      "lng": 126.42581
    },
    {
      "rank": 1,
      "name": "대학사로또복권",
      "address": "경남 창원시 성산구 상남동 10-5피아노빌딩101호(패밀리마트內)",
      "method": "auto",
      "lat": 35.221687,
      "lng": 128.68623
    }
  ]
}